{
  "120363409149646282@g.us": {
    "listBadword": [
      "bego"
    ],
    "createdAt": "2026-04-21T13:34:57.530Z",
    "updatedAt": "2026-04-21T13:34:57.536Z"
  },
  "120363425984714150@g.us": {
    "listBadword": [],
    "createdAt": "2026-04-25T11:31:30.884Z",
    "updatedAt": "2026-04-25T11:31:30.884Z"
  },
  "global-badword": {
    "listBadword": [],
    "createdAt": "2026-04-25T11:31:31.191Z",
    "updatedAt": "2026-04-25T11:31:31.193Z"
  },
  "120363424127805653@g.us": {
    "listBadword": [],
    "createdAt": "2026-06-04T01:46:45.523Z",
    "updatedAt": "2026-06-04T01:46:45.523Z"
  },
  "120363427365229377@g.us": {
    "listBadword": [
      "tolol",
      "jnck",
      "kacung",
      "cung",
      "cunk",
      "Cok",
      "Asu",
      "tempek",
      "4su",
      "tuempek",
      "JANCOX",
      "anjing"
    ],
    "createdAt": "2026-06-13T00:22:34.216Z",
    "updatedAt": "2026-06-13T01:10:52.079Z"
  }
}